Ellmental/__init__.py
Ellmental/ellmental.py
eLLMental-0.1.3.dist-info/METADATA
eLLMental-0.1.3.dist-info/WHEEL
eLLMental-0.1.3.dist-info/top_level.txt
eLLMental-0.1.3.dist-info/RECORD
