Metadata-Version: 2.1
Name: eLLMental
Version: 0.1.3
Summary: Pytohn SDK for eLLMental
Home-page: https://github.com/theam/eLLMental_python_sdk
Author: eLLMental
Author-email: info@theagilemonkeys.com
Classifier: Programming Language :: Python :: 3
Classifier: Operating System :: OS Independent
Requires-Python: >=3.6
Requires-Dist: requests
